openremote_client/__init__.py
openremote_client/authenticator.py
openremote_client/http.py
openremote_client/response.py
openremote_client/url_builder.py
openremote_client/api/__init__.py
openremote_client/api/agent.py
openremote_client/api/alarm.py
openremote_client/api/asset.py
openremote_client/api/asset_datapoint.py
openremote_client/api/asset_model.py
openremote_client/api/asset_predicted_datapoint.py
openremote_client/api/configuration.py
openremote_client/api/console.py
openremote_client/api/dashboard.py
openremote_client/api/flow.py
openremote_client/api/gateway.py
openremote_client/api/map.py
openremote_client/api/notification.py
openremote_client/api/provisioning.py
openremote_client/api/realm.py
openremote_client/api/rule.py
openremote_client/api/services.py
openremote_client/api/status.py
openremote_client/api/syslog.py
openremote_client/api/ui_apps.py
openremote_client/api/user.py
openremote_client/schemas/__init__.py
openremote_client/schemas/abstract_notification_message.py
openremote_client/schemas/agent_descriptor.py
openremote_client/schemas/agent_object_object_object.py
openremote_client/schemas/alarm.py
openremote_client/schemas/alarm_asset_link.py
openremote_client/schemas/allowed_values.py
openremote_client/schemas/array_predicate.py
openremote_client/schemas/asset_conditions.py
openremote_client/schemas/asset_datapoint_all_query.py
openremote_client/schemas/asset_datapoint_interval_query.py
openremote_client/schemas/asset_datapoint_lttb_query.py
openremote_client/schemas/asset_datapoint_nearest_query.py
openremote_client/schemas/asset_datapoint_query.py
openremote_client/schemas/asset_descriptor_object.py
openremote_client/schemas/asset_object.py
openremote_client/schemas/asset_query.py
openremote_client/schemas/asset_ruleset.py
openremote_client/schemas/asset_tree.py
openremote_client/schemas/asset_tree_asset.py
openremote_client/schemas/asset_tree_node.py
openremote_client/schemas/asset_type_info.py
openremote_client-1.0.2.dist-info/licenses/LICENSE.txt
openremote_client-1.0.2.dist-info/METADATA
openremote_client-1.0.2.dist-info/WHEEL
openremote_client-1.0.2.dist-info/top_level.txt
openremote_client-1.0.2.dist-info/RECORD
